<?xml version="1.0" encoding="utf-8" ?>
<RecipeDefs>

<!-- ===========--> 
   <RecipeDef>
    <defName>MP40Craft</defName>
    <label>Make MP40</label>
    <description>Craft MP40.</description>
    <jobString>Making MP40</jobString>
	<unfinishedThingDef>UnfinishedWeapon</unfinishedThingDef>
	<workSpeedStat>SmithingSpeed</workSpeedStat>
    <workAmount>80000</workAmount>
	<workSkill>Crafting</workSkill>
    <products>
        <Gun_MP40_rt>1</Gun_MP40_rt>
    </products>
    <ingredients>
		<li>
			<filter>
				<thingDefs>
					<li>Steel</li>
				</thingDefs>
			</filter>
			<count>100</count>
		</li>
		<li>
			<filter>
				<thingDefs>
					<li>Component</li>
				</thingDefs>
			</filter>
			<count>2</count>
		</li>
		<li>
			<filter>
				<thingDefs>
					<li>WoodLog</li>
				</thingDefs>
			</filter>
			<count>1</count>
		</li>
    </ingredients>
	<fixedIngredientFilter>
         <thingDefs>
            <li>Steel</li>
			<li>Component</li>
			<li>WoodLog</li>
         </thingDefs>
    </fixedIngredientFilter>
	<recipeUsers>
		<li>WeaponAssemblyTable_RT</li>
	</recipeUsers>
	<researchPrerequisite>Smgs_RT</researchPrerequisite>
	<skillRequirements>
		<li>
			<skill>Crafting</skill>
			<minLevel>5</minLevel>
		</li>
	</skillRequirements>
  </RecipeDef>  

<!-- ===========--> 
   <RecipeDef>
    <defName>Skorpionvz61Craft</defName>
    <label>Make Skorpion vz.61</label>
    <description>Craft Skorpion vz.61.</description>
    <jobString>Making Skorpion vz.61.</jobString>
	<unfinishedThingDef>UnfinishedWeapon</unfinishedThingDef>
	<workSpeedStat>SmithingSpeed</workSpeedStat>
    <workAmount>38000</workAmount>
	<workSkill>Crafting</workSkill>
    <products>
        <Gun_Skorpionvz61_rt>1</Gun_Skorpionvz61_rt>
    </products>
    <ingredients>
		<li>
			<filter>
				<thingDefs>
					<li>Steel</li>
				</thingDefs>
			</filter>
			<count>40</count>
		</li>
		<li>
			<filter>
				<thingDefs>
					<li>Component</li>
				</thingDefs>
			</filter>
			<count>2</count>
		</li>
    </ingredients>
	<fixedIngredientFilter>
         <thingDefs>
            <li>Steel</li>
			<li>Component</li>
         </thingDefs>
    </fixedIngredientFilter>
	<recipeUsers>
		<li>WeaponAssemblyTable_RT</li>
	</recipeUsers>
	<researchPrerequisite>Smgs_RT</researchPrerequisite>
	<skillRequirements>
		<li>
			<skill>Crafting</skill>
			<minLevel>5</minLevel>
		</li>
	</skillRequirements>
  </RecipeDef>

<!-- ===========--> 
   <RecipeDef>
    <defName>UziCraft</defName>
    <label>Make Uzi</label>
    <description>Craft Uzi.</description>
    <jobString>Making Uzi.</jobString>
	<unfinishedThingDef>UnfinishedWeapon</unfinishedThingDef>
	<workSpeedStat>SmithingSpeed</workSpeedStat>
    <workAmount>68000</workAmount>
	<workSkill>Crafting</workSkill>
    <products>
        <Gun_Uzi_rt>1</Gun_Uzi_rt>
    </products>
    <ingredients>
		<li>
			<filter>
				<thingDefs>
					<li>Steel</li>
				</thingDefs>
			</filter>
			<count>80</count>
		</li>
		<li>
			<filter>
				<thingDefs>
					<li>Component</li>
				</thingDefs>
			</filter>
			<count>2</count>
		</li>
    </ingredients>
	<fixedIngredientFilter>
         <thingDefs>
            <li>Steel</li>
			<li>Component</li>
         </thingDefs>
    </fixedIngredientFilter>
	<recipeUsers>
		<li>WeaponAssemblyTable_RT</li>
	</recipeUsers>
	<researchPrerequisite>Smgs_RT</researchPrerequisite>
	<skillRequirements>
		<li>
			<skill>Crafting</skill>
			<minLevel>5</minLevel>
		</li>
	</skillRequirements>
  </RecipeDef>
  
  
<!-- ===========--> 
   <RecipeDef>
    <defName>HKMP7Craft</defName>
    <label>Make HK MP7</label>
    <description>Craft HK MP7.</description>
    <jobString>Making HK MP7.</jobString>
	<unfinishedThingDef>UnfinishedWeapon</unfinishedThingDef>
	<workSpeedStat>SmithingSpeed</workSpeedStat>
    <workAmount>78000</workAmount>
	<workSkill>Crafting</workSkill>
    <products>
        <Gun_HKMP7_rt>1</Gun_HKMP7_rt>
    </products>
    <ingredients>
		<li>
			<filter>
				<thingDefs>
					<li>Steel</li>
				</thingDefs>
			</filter>
			<count>67</count>
		</li>
		<li>
			<filter>
				<thingDefs>
					<li>Component</li>
				</thingDefs>
			</filter>
			<count>2</count>
		</li>
    </ingredients>
	<fixedIngredientFilter>
         <thingDefs>
            <li>Steel</li>
			<li>Component</li>
         </thingDefs>
    </fixedIngredientFilter>
	<recipeUsers>
		<li>WeaponAssemblyTable_RT</li>
	</recipeUsers>
	<researchPrerequisite>Smgs_RT</researchPrerequisite>
	<skillRequirements>
		<li>
			<skill>Crafting</skill>
			<minLevel>5</minLevel>
		</li>
	</skillRequirements>
  </RecipeDef>
<!-- ===========--> 
   <RecipeDef>
    <defName>CZ3A1Craft</defName>
    <label>Make CZ-3A1</label>
    <description>Craft CZ-3A1.</description>
    <jobString>Making CZ-3A1.</jobString>
	<unfinishedThingDef>UnfinishedWeapon</unfinishedThingDef>
	<workSpeedStat>SmithingSpeed</workSpeedStat>
    <workAmount>80000</workAmount>
	<workSkill>Crafting</workSkill>
    <products>
        <Gun_CZ3A1_rt>1</Gun_CZ3A1_rt>
    </products>
    <ingredients>
		<li>
			<filter>
				<thingDefs>
					<li>Steel</li>
				</thingDefs>
			</filter>
			<count>80</count>
		</li>
		<li>
			<filter>
				<thingDefs>
					<li>Component</li>
				</thingDefs>
			</filter>
			<count>2</count>
		</li>
    </ingredients>
	<fixedIngredientFilter>
         <thingDefs>
            <li>Steel</li>
			<li>Component</li>
         </thingDefs>
    </fixedIngredientFilter>
	<recipeUsers>
		<li>WeaponAssemblyTable_RT</li>
	</recipeUsers>
	<researchPrerequisite>Smgs_RT</researchPrerequisite>	
	<skillRequirements>
		<li>
			<skill>Crafting</skill>
			<minLevel>5</minLevel>
		</li>
	</skillRequirements>
  </RecipeDef>
 

<!-- ===========--> 
   <RecipeDef>
    <defName>KRISSVectorCraft</defName>
    <label>Make KRISS Vector</label>
    <description>Craft KRISS Vector.</description>
    <jobString>Making KRISS Vector.</jobString>
	<unfinishedThingDef>UnfinishedWeapon</unfinishedThingDef>
	<workSpeedStat>SmithingSpeed</workSpeedStat>
    <workAmount>90000</workAmount>
	<workSkill>Crafting</workSkill>
    <products>
        <Gun_KRISSvector_rt>1</Gun_KRISSvector_rt>
    </products>
    <ingredients>
		<li>
			<filter>
				<thingDefs>
					<li>Steel</li>
				</thingDefs>
			</filter>
			<count>90</count>
		</li>
		<li>
			<filter>
				<thingDefs>
					<li>Component</li>
				</thingDefs>
			</filter>
			<count>2</count>
		</li>
    </ingredients>
	<fixedIngredientFilter>
         <thingDefs>
            <li>Steel</li>
			<li>Component</li>
         </thingDefs>
    </fixedIngredientFilter>
	<recipeUsers>
		<li>WeaponAssemblyTable_RT</li>
	</recipeUsers>
	<researchPrerequisite>Smgs_RT</researchPrerequisite>
	<skillRequirements>
		<li>
			<skill>Crafting</skill>
			<minLevel>5</minLevel>
		</li>
	</skillRequirements>
  </RecipeDef>
 
<!-- ===========--> 
   <RecipeDef>
    <defName>HKUMP45Craft</defName>
    <label>Make HK UMP45</label>
    <description>Craft HK UMP45.</description>
    <jobString>Making HK UMP45.</jobString>
	<unfinishedThingDef>UnfinishedWeapon</unfinishedThingDef>
	<workSpeedStat>SmithingSpeed</workSpeedStat>
    <workAmount>78000</workAmount>
	<workSkill>Crafting</workSkill>
    <products>
        <Gun_HK_UMP45_rt>1</Gun_HK_UMP45_rt>
    </products>
    <ingredients>
		<li>
			<filter>
				<thingDefs>
					<li>Steel</li>
				</thingDefs>
			</filter>
			<count>67</count>
		</li>
		<li>
			<filter>
				<thingDefs>
					<li>Component</li>
				</thingDefs>
			</filter>
			<count>1</count>
		</li>
    </ingredients>
	<fixedIngredientFilter>
         <thingDefs>
            <li>Steel</li>
			<li>Component</li>
         </thingDefs>
    </fixedIngredientFilter>
	<recipeUsers>
		<li>WeaponAssemblyTable_RT</li>
	</recipeUsers>
	<researchPrerequisite>Smgs_RT</researchPrerequisite>
	<skillRequirements>
		<li>
			<skill>Crafting</skill>
			<minLevel>5</minLevel>
		</li>
	</skillRequirements>
  </RecipeDef>

  
  
<!-- ===========--> 
   <RecipeDef>
    <defName>FNP90Craft</defName>
    <label>Make FN P90</label>
    <description>Craft FNP90.</description>
    <jobString>Making FNP90.</jobString>
	<unfinishedThingDef>UnfinishedWeapon</unfinishedThingDef>
	<workSpeedStat>SmithingSpeed</workSpeedStat>
    <workAmount>78000</workAmount>
	<workSkill>Crafting</workSkill>
    <products>
        <Gun_P90_rt>1</Gun_P90_rt>
    </products>
    <ingredients>
		<li>
			<filter>
				<thingDefs>
					<li>Steel</li>
				</thingDefs>
			</filter>
			<count>75</count>
		</li>
		<li>
			<filter>
				<thingDefs>
					<li>Component</li>
				</thingDefs>
			</filter>
			<count>2</count>
		</li>
    </ingredients>
	<fixedIngredientFilter>
         <thingDefs>
            <li>Steel</li>
			<li>Component</li>
         </thingDefs>
    </fixedIngredientFilter>
	<recipeUsers>
		<li>WeaponAssemblyTable_RT</li>
	</recipeUsers>
	<researchPrerequisite>Smgs_RT</researchPrerequisite>
	<skillRequirements>
		<li>
			<skill>Crafting</skill>
			<minLevel>5</minLevel>
		</li>
	</skillRequirements>
  </RecipeDef>  
  
<!-- ===========--> 
   <RecipeDef>
    <defName>TSMGCraft</defName>
    <label>Make Thompson Submachine Gun</label>
    <description>Craft Thompson Submachine Gun.</description>
    <jobString>Making Thompson Submachine Gun.</jobString>
	<unfinishedThingDef>UnfinishedWeapon</unfinishedThingDef>
	<workSpeedStat>SmithingSpeed</workSpeedStat>
    <workAmount>100000</workAmount>
	<workSkill>Crafting</workSkill>
    <products>
        <Gun_Thompson_Submachine_Gun_rt>1</Gun_Thompson_Submachine_Gun_rt>
    </products>
    <ingredients>
		<li>
			<filter>
				<thingDefs>
					<li>Steel</li>
				</thingDefs>
			</filter>
			<count>115</count>
		</li>
		<li>
			<filter>
				<thingDefs>
					<li>Component</li>
				</thingDefs>
			</filter>
			<count>2</count>
		</li>
		<li>
			<filter>
				<thingDefs>
					<li>WoodLog</li>
				</thingDefs>
			</filter>
			<count>2</count>
		</li>
    </ingredients>
	<fixedIngredientFilter>
         <thingDefs>
            <li>Steel</li>
			<li>Component</li>
			<li>WoodLog</li>
         </thingDefs>
    </fixedIngredientFilter>
	<recipeUsers>
		<li>WeaponAssemblyTable_RT</li>
	</recipeUsers>
	<researchPrerequisite>Smgs_RT</researchPrerequisite>
	<skillRequirements>
		<li>
			<skill>Crafting</skill>
			<minLevel>5</minLevel>
		</li>
	</skillRequirements>
  </RecipeDef>  


<!-- ===========--> 
   <RecipeDef>
    <defName>PPSH41Craft</defName>
    <label>Make PPSH-41</label>
    <description>Craft PPSH-41.</description>
    <jobString>Making PPSH-41.</jobString>
	<unfinishedThingDef>UnfinishedWeapon</unfinishedThingDef>
	<workSpeedStat>SmithingSpeed</workSpeedStat>
    <workAmount>110000</workAmount>
	<workSkill>Crafting</workSkill>
    <products>
        <Gun_PPSH_41_rt>1</Gun_PPSH_41_rt>
    </products>
    <ingredients>
		<li>
			<filter>
				<thingDefs>
					<li>Steel</li>
				</thingDefs>
			</filter>
			<count>110</count>
		</li>
		<li>
			<filter>
				<thingDefs>
					<li>Component</li>
				</thingDefs>
			</filter>
			<count>3</count>
		</li>
		<li>
			<filter>
				<thingDefs>
					<li>WoodLog</li>
				</thingDefs>
			</filter>
			<count>2</count>
		</li>
    </ingredients>
	<fixedIngredientFilter>
         <thingDefs>
            <li>Steel</li>
			<li>Component</li>
			<li>WoodLog</li>
         </thingDefs>
    </fixedIngredientFilter>
	<recipeUsers>
		<li>WeaponAssemblyTable_RT</li>
	</recipeUsers>
	<researchPrerequisite>Smgs_RT</researchPrerequisite>
	<skillRequirements>
		<li>
			<skill>Crafting</skill>
			<minLevel>5</minLevel>
		</li>
	</skillRequirements>
  </RecipeDef> 
  
</RecipeDefs>